pygsm/__init__.py
pygsm/coordinate_systems/__init__.py
pygsm/coordinate_systems/cartesian.py
pygsm/coordinate_systems/delocalized_coordinates.py
pygsm/coordinate_systems/internal_coordinates.py
pygsm/coordinate_systems/primitive_internals.py
pygsm/coordinate_systems/rotate.py
pygsm/coordinate_systems/slots.py
pygsm/coordinate_systems/topology.py
pygsm/dynamics/__init__.py
pygsm/growing_string_methods/__init__.py
pygsm/growing_string_methods/de_gsm.py
pygsm/growing_string_methods/gsm.py
pygsm/growing_string_methods/main_gsm.py
pygsm/growing_string_methods/se_cross.py
pygsm/growing_string_methods/se_gsm.py
pygsm/level_of_theories/__init__.py
pygsm/level_of_theories/ase.py
pygsm/level_of_theories/bagel.py
pygsm/level_of_theories/base_lot.py
pygsm/level_of_theories/dftb.py
pygsm/level_of_theories/file_options.py
pygsm/level_of_theories/gaussian.py
pygsm/level_of_theories/molpro.py
pygsm/level_of_theories/nanoreactor_engine.py
pygsm/level_of_theories/openmm.py
pygsm/level_of_theories/orca.py
pygsm/level_of_theories/pdynamo.py
pygsm/level_of_theories/pytc.py
pygsm/level_of_theories/qchem.py
pygsm/level_of_theories/terachem.py
pygsm/level_of_theories/terachemcloud.py
pygsm/level_of_theories/xtb_lot.py
pygsm/optimizers/__init__.py
pygsm/optimizers/_linesearch.py
pygsm/optimizers/base_optimizer.py
pygsm/optimizers/beales_cg.py
pygsm/optimizers/conjugate_gradient.py
pygsm/optimizers/eigenvector_follow.py
pygsm/optimizers/lbfgs.py
pygsm/potential_energy_surfaces/__init__.py
pygsm/potential_energy_surfaces/avg_pes.py
pygsm/potential_energy_surfaces/penalty_pes.py
pygsm/potential_energy_surfaces/pes.py
pygsm/utilities/__init__.py
pygsm/utilities/block_matrix.py
pygsm/utilities/block_tensor.py
pygsm/utilities/elements.py
pygsm/utilities/manage_xyz.py
pygsm/utilities/math_utils.py
pygsm/utilities/nifty.py
pygsm/utilities/options.py
pygsm/utilities/random_quotes.py
pygsm/utilities/units.py
pygsm/wrappers/__init__.py
pygsm/wrappers/ase.py
pygsm/wrappers/main.py
pygsm_gaussian-1.0.1.dist-info/LICENSE
pygsm_gaussian-1.0.1.dist-info/METADATA
pygsm_gaussian-1.0.1.dist-info/WHEEL
pygsm_gaussian-1.0.1.dist-info/entry_points.txt
pygsm_gaussian-1.0.1.dist-info/top_level.txt
pygsm_gaussian-1.0.1.dist-info/RECORD
