Metadata-Version: 2.1
Name: pygsm-gaussian
Version: 1.0.1
Summary: Reaction path searching
Home-page: https://github.com/ZimmermanGroup/pyGSM
Author: Cody Aldaz
Author-email: codyaldaz@gmail.com
License-File: LICENSE
Requires-Dist: numpy (>=1.11)
Requires-Dist: networkx
Requires-Dist: scipy (>=1.1.0)
Requires-Dist: six
Requires-Dist: matplotlib
Requires-Dist: py3Dmol
